hafezR/__init__.py
hafezR/__main__.py
hafezR/install_deps.py
hafezr-0.1.0.dist-info/METADATA
hafezr-0.1.0.dist-info/WHEEL
hafezr-0.1.0.dist-info/entry_points.txt
hafezr-0.1.0.dist-info/top_level.txt
hafezr-0.1.0.dist-info/RECORD
