Metadata-Version: 2.4
Name: hafezR
Version: 0.1.0
Summary: Setup script to install GCC and configure R Makevars for the hafez package.
Author: Your Name
Requires-Python: >=3.6
Dynamic: author
Dynamic: requires-python
Dynamic: summary
